jug_schedule/__init__.py
jug_schedule/errors.py
jug_schedule/queues.py
jug_schedule/resources.py
jug_schedule/schedule.py
jug_schedule/version.py
jug_schedule-0.4.2.dist-info/DESCRIPTION.rst
jug_schedule-0.4.2.dist-info/METADATA
jug_schedule-0.4.2.dist-info/RECORD
jug_schedule-0.4.2.dist-info/WHEEL
jug_schedule-0.4.2.dist-info/metadata.json
jug_schedule-0.4.2.dist-info/top_level.txt
