Metadata-Version: 2.0
Name: jug-schedule
Version: 0.4.2
Summary: Automatic DRMAA scheduling with resource management for Jug
Home-page: https://gitlab.com/Unode/jug_schedule
Author: Renato Alves
Author-email: alves.rjc@gmail.com
License: MIT
Platform: Any
Classifier: Development Status :: 4 - Beta
Classifier: Environment :: Console
Classifier: License :: OSI Approved :: MIT License
Classifier: Operating System :: POSIX
Classifier: Operating System :: OS Independent
Classifier: Programming Language :: Python
Classifier: Programming Language :: Python :: 2
Classifier: Programming Language :: Python :: 2.7
Classifier: Programming Language :: Python :: 3
Classifier: Programming Language :: Python :: 3.3
Classifier: Programming Language :: Python :: 3.4
Classifier: Programming Language :: Python :: 3.5
Classifier: Programming Language :: Python :: 3.6
Classifier: Topic :: Scientific/Engineering
Classifier: Topic :: Software Development
Classifier: Topic :: System :: Distributed Computing
Classifier: Intended Audience :: Science/Research
Requires-Dist: colorlog
Requires-Dist: drmaa
Requires-Dist: jug (>1.4.0)
